{"parentSha1":"23ec1910db007767a136eb052bcce24617af132e","path":"books/Topology Without Tears/1. Topological Spaces/1.1 Topology/5","kids":[],"item":{"attr":{"a":"(i) $\\tau_{1}$ consists of $\\mathbb{R}$, $\\emptyset$, and every interval $(-n,n)$, for $n$ any positive integer;\n\n> $\\tau_1$ is a topology.  \n> Let $A$ be the union of finite or infinite number of sets. If there is an upper bound $u$ then $A$ will be $(-u, u)$. If there is not an upper bound, then $A$ will be $\\mathbb{R}$.  \n> Let $B$ be the intersection of any $(-a,a)$ and $(-b,b)$. And let's say $a$ is smaller than $b$ without loss of generality. Then $B$ will be $(-a,a)$.\n\n(ii) $\\tau_{2}$ consists of $\\mathbb{R}$, $\\emptyset$, and every interval $[-n,n]$, for $n$ any positive integer;\n> $\\tau_2$ is not a topology. Union of infinite sets of $[-k, k]$ such that every $k < n$ is $(-n, n)$\n\n(iii) $\\tau_{3}$ consists of $\\mathbb{R}$, $\\emptyset$, and every interval $[-n,\\infty)$, for $n$ any positive integer;\n> $\\tau_3$ is not a topology. For the same reason of (ii), you can deduce that $(-n, \\infty)$ is open.\n","q":"Let $\\mathbb{R}$ be the set of all real numbers. Prove that each of the following collections subsets or $\\mathbb{R}$ is a topology."},"sha1":"7799852669635560f5c2deb1864e1dbc32895950","title":"5"}}