{"parentSha1":"c93296043264cf88e124ad31ce4a81d5c9787792","path":"books/Introduction to Probability, Statistics, and Random Processes/1.5.0/22","kids":[],"item":{"attr":{"a":"Let $`F`$ be the event that the customer buys a cup of coffee, $`K`$ a piece of cake.\n\n```math\n\\begin{aligned}\n  &P(F, K) = 0.2 \\\\\n  &\\rightarrow P(F|K)P(K) = 0.2 \\\\\n  &\\rightarrow P(F|K) * 0.7 = 0.2 \\\\\n  &\\rightarrow P(F|K) = \\frac{2}{7} \\\\\n\\end{aligned}\n```","q":"Suppose that, of all the customers at a coffee shop,\n\n* 70% purchase a cup of coffee;\n* 40% purchase a piece of cake;\n* 20% purchase both a cup of coffee and a piece of cake.\n\nGiven that a randomly chosen customer has purchased a piece of cake, what is the probability that he/she has also purchased a cup of coffee?"},"sha1":"80e5b9017c7f7f11649297eed2e8788ee57b2337","title":"22"}}